wordle/__init__.py
wordle/dictionary.py
wordle/randomanswer.py
wordle/wordle.py
wordle_python-2.4.0.dist-info/METADATA
wordle_python-2.4.0.dist-info/WHEEL
wordle_python-2.4.0.dist-info/top_level.txt
wordle_python-2.4.0.dist-info/RECORD
