Metadata-Version: 2.1
Name: wordle-python
Version: 2.4.0
Summary: The popular word game recreated in Python, deployable with custom answers.
Author: Prerit Das
Author-email: <preritdas@gmail.com>
Keywords: python,games,wordle,english,word games
Classifier: Programming Language :: Python :: 3
Classifier: Operating System :: Unix
Classifier: Operating System :: MacOS :: MacOS X
Classifier: Operating System :: Microsoft :: Windows
